codefury/__init__.py
codefury-0.1.0.dist-info/METADATA
codefury-0.1.0.dist-info/WHEEL
codefury-0.1.0.dist-info/RECORD
