Metadata-Version: 2.3
Name: codefury
Version: 0.1.0
Summary: The single agent to make your production burn
Author: Michał Murawski
Author-email: mmurawski777@gmail.com
Requires-Python: >=3.12
Classifier: Programming Language :: Python :: 3
Classifier: Programming Language :: Python :: 3.12
Classifier: Programming Language :: Python :: 3.13
